Classfile /E:/__PROJECT__/JAVA/BookShildt_001/out/production/BookShildt_001/e0028_ObjectAsParameter/Test.class
  Last modified 25 окт. 2022 г.; size 564 bytes
  SHA-256 checksum 29278e123ed775e4958cb6b32a7a8967a5edce912de6524b4d31ca643a3bfff9
  Compiled from "Test.java"
class e0028_ObjectAsParameter.Test
  minor version: 0
  major version: 61
  flags: (0x0020) ACC_SUPER
  this_class: #8                          // e0028_ObjectAsParameter/Test
  super_class: #2                         // java/lang/Object
  interfaces: 0, fields: 2, methods: 2, attributes: 1
Constant pool:
   #1 = Methodref          #2.#3          // java/lang/Object."<init>":()V
   #2 = Class              #4             // java/lang/Object
   #3 = NameAndType        #5:#6          // "<init>":()V
   #4 = Utf8               java/lang/Object
   #5 = Utf8               <init>
   #6 = Utf8               ()V

   #7 = Fieldref           #8.#9          // e0028_ObjectAsParameter/Test.a:I
   #8 = Class              #10            // e0028_ObjectAsParameter/Test
   #9 = NameAndType        #11:#12        // a:I
  #10 = Utf8               e0028_ObjectAsParameter/Test
  #11 = Utf8               a

  #12 = Utf8               I

  #13 = Fieldref           #8.#14         // e0028_ObjectAsParameter/Test.b:I
  #14 = NameAndType        #15:#12        // b:I
  #15 = Utf8               b

  #16 = Utf8               (II)V
  #17 = Utf8               Code
  #18 = Utf8               LineNumberTable
  #19 = Utf8               LocalVariableTable
  #20 = Utf8               this
  #21 = Utf8               Le0028_ObjectAsParameter/Test;
  #22 = Utf8               i
  #23 = Utf8               j
  #24 = Utf8               equalTo
  #25 = Utf8               (Le0028_ObjectAsParameter/Test;)Z
  #26 = Utf8               obj
  #27 = Utf8               StackMapTable
  #28 = Utf8               SourceFile
  #29 = Utf8               Test.java
{
  int a;
    descriptor: I
    flags: (0x0000)

  int b;
    descriptor: I
    flags: (0x0000)

  e0028_ObjectAsParameter.Test(int, int);
    descriptor: (II)V
    flags: (0x0000)
    Code:
      stack=2, locals=3, args_size=3
         0: aload_0
         1: invokespecial #1                  // Method java/lang/Object."<init>":()V

         4: aload_0
         5: iload_1
         6: putfield      #7                  // Field a:I
         
         9: aload_0
        10: iload_2
        11: putfield      #13                 // Field b:I
        14: return
      LineNumberTable:
        line 7: 0
        line 8: 4
        line 9: 9
        line 10: 14
      LocalVariableTable:
        Start  Length  Slot  Name   Signature
            0      15     0  this   Le0028_ObjectAsParameter/Test;
            0      15     1     i   I
            0      15     2     j   I

  boolean equalTo(e0028_ObjectAsParameter.Test);
    descriptor: (Le0028_ObjectAsParameter/Test;)Z
    flags: (0x0000)
    Code:
      stack=2, locals=2, args_size=2
         0: aload_1
         1: getfield      #7                  // Field a:I
         4: aload_0
         5: getfield      #7                  // Field a:I
         
         8: if_icmpne     24
         
        11: aload_1
        12: getfield      #13                 // Field b:I
        15: aload_0
        16: getfield      #13                 // Field b:I

        19: if_icmpne     24
        
        22: iconst_1
        23: ireturn
        
        24: iconst_0
        25: ireturn
      LineNumberTable:
        line 13: 0
        line 14: 24
      LocalVariableTable:
        Start  Length  Slot  Name   Signature
            0      26     0  this   Le0028_ObjectAsParameter/Test;
            0      26     1   obj   Le0028_ObjectAsParameter/Test;
      StackMapTable: number_of_entries = 1
        frame_type = 24 /* same */
}
SourceFile: "Test.java"
#############################################################################################
package e0028_ObjectAsParameter;

class Test {
    int a;
    int b;

    Test(int i, int j) {
        a = i;
        b = j;
    }

    boolean equalTo(Test obj) {
        if (obj.a == a && obj.b == b) return true;
        else return false;
    }
}
---------------------------------------------------------------------------------------------
